eda_simple.py
plot.py
process.py
txt2pkl.py
edamam123-0.0.4.dist-info/METADATA
edamam123-0.0.4.dist-info/WHEEL
edamam123-0.0.4.dist-info/top_level.txt
edamam123-0.0.4.dist-info/RECORD
